itk/Configuration/RansacConfig.py
itk/Configuration/Ransac_snake_case.py
itk/RansacPython.py
itk/_RansacPython.so
itk/itkRansacPython.py
itk_ransac-0.2.1.dist-info/METADATA
itk_ransac-0.2.1.dist-info/WHEEL
itk_ransac-0.2.1.dist-info/licenses/LICENSE
itk_ransac-0.2.1.dist-info/RECORD
