Metadata-Version: 2.1
Name: itk-ransac
Version: 0.2.1
Summary: It supports feature based registration and can be used along with the FPFH remote module. The class itkRANSAC is the main driver that takes an object of class itkLandmarkRegistrationEstimator as argument. Please refer to the documentation for a detailed description and sample usage: https://github.com/InsightSoftwareConsortium/ITKRANSAC.
Keywords: itk
Author-Email: Pranjal Sahu <pranjalsahu5@gmail.com>
License:                                  Apache License
Classifier: Development Status :: 4 - Beta
Classifier: Intended Audience :: Developers
Classifier: Intended Audience :: Education
Classifier: Intended Audience :: Healthcare Industry
Classifier: Intended Audience :: Science/Research
Classifier: License :: OSI Approved :: Apache Software License
Classifier: Operating System :: Android
Classifier: Operating System :: MacOS
Classifier: Operating System :: Microsoft :: Windows
Classifier: Operating System :: POSIX
Classifier: Operating System :: Unix
Classifier: Programming Language :: C++
Classifier: Programming Language :: Python
Classifier: Topic :: Scientific/Engineering
Classifier: Topic :: Scientific/Engineering :: Information Analysis
Classifier: Topic :: Scientific/Engineering :: Medical Science Apps.
Classifier: Topic :: Software Development :: Libraries
Project-URL: Download, https://github.com/InsightSoftwareConsortium/ITKRANSAC
Project-URL: Homepage, https://github.com/InsightSoftwareConsortium/ITKRANSAC
Requires-Python: >=3.8
Requires-Dist: itk==5.4.*
License-File: LICENSE
